gallery_dl/__init__.py
gallery_dl/__main__.py
gallery_dl/actions.py
gallery_dl/aes.py
gallery_dl/archive.py
gallery_dl/cache.py
gallery_dl/config.py
gallery_dl/cookies.py
gallery_dl/dt.py
gallery_dl/exception.py
gallery_dl/formatter.py
gallery_dl/job.py
gallery_dl/oauth.py
gallery_dl/option.py
gallery_dl/output.py
gallery_dl/path.py
gallery_dl/text.py
gallery_dl/transaction_id.py
gallery_dl/update.py
gallery_dl/util.py
gallery_dl/version.py
gallery_dl/ytdl.py
gallery_dl/downloader/__init__.py
gallery_dl/downloader/common.py
gallery_dl/downloader/http.py
gallery_dl/downloader/text.py
gallery_dl/downloader/ytdl.py
gallery_dl/extractor/2ch.py
gallery_dl/extractor/2chan.py
gallery_dl/extractor/2chen.py
gallery_dl/extractor/35photo.py
gallery_dl/extractor/3dbooru.py
gallery_dl/extractor/4archive.py
gallery_dl/extractor/4chan.py
gallery_dl/extractor/4chanarchives.py
gallery_dl/extractor/500px.py
gallery_dl/extractor/8chan.py
gallery_dl/extractor/8muses.py
gallery_dl/extractor/__init__.py
gallery_dl/extractor/adultempire.py
gallery_dl/extractor/agnph.py
gallery_dl/extractor/ahottie.py
gallery_dl/extractor/ao3.py
gallery_dl/extractor/arcalive.py
gallery_dl/extractor/architizer.py
gallery_dl/extractor/arena.py
gallery_dl/extractor/artstation.py
gallery_dl/extractor/aryion.py
gallery_dl/extractor/audiochan.py
gallery_dl/extractor/bbc.py
gallery_dl/extractor/behance.py
gallery_dl/extractor/bellazon.py
gallery_dl/extractor/bilibili.py
gallery_dl/extractor/blogger.py
gallery_dl/extractor/bluesky.py
gallery_dl/extractor/booru.py
gallery_dl/extractor/boosty.py
gallery_dl/extractor/booth.py
gallery_dl/extractor/bunkr.py
gallery_dl/extractor/catbox.py
gallery_dl/extractor/cfake.py
gallery_dl/extractor/chevereto.py
gallery_dl/extractor/cien.py
gallery_dl/extractor/civitai.py
gallery_dl/extractor/comedywildlifephoto.py
gallery_dl/extractor/comick.py
gallery_dl/extractor/comicvine.py
gallery_dl/extractor/common.py
gallery_dl/extractor/cyberdrop.py
gallery_dl/extractor/cyberfile.py
gallery_dl-1.31.5.dist-info/licenses/LICENSE
gallery_dl-1.31.5.dist-info/METADATA
gallery_dl-1.31.5.dist-info/WHEEL
gallery_dl-1.31.5.dist-info/entry_points.txt
gallery_dl-1.31.5.dist-info/top_level.txt
gallery_dl-1.31.5.dist-info/RECORD
