Metadata-Version: 2.4
Name: gallery_dl
Version: 1.31.5
Summary: Command-line program to download image galleries and collections from several image hosting sites
Home-page: https://github.com/mikf/gallery-dl
Download-URL: https://github.com/mikf/gallery-dl/releases/latest
Author: Mike Fährmann
Author-email: mike_faehrmann@web.de
Maintainer: Mike Fährmann
Maintainer-email: mike_faehrmann@web.de
License: GPL-2.0-only
Keywords: image gallery downloader crawler scraper
Classifier: Development Status :: 5 - Production/Stable
Classifier: Environment :: Console
Classifier: Intended Audience :: End Users/Desktop
Classifier: License :: OSI Approved :: GNU General Public License v2 (GPLv2)
Classifier: Operating System :: OS Independent
Classifier: Programming Language :: Python
Classifier: Programming Language :: Python :: 3
Classifier: Programming Language :: Python :: 3 :: Only
Classifier: Programming Language :: Python :: 3.8
Classifier: Programming Language :: Python :: 3.9
Classifier: Programming Language :: Python :: 3.10
Classifier: Programming Language :: Python :: 3.11
Classifier: Programming Language :: Python :: 3.12
Classifier: Programming Language :: Python :: 3.13
Classifier: Programming Language :: Python :: 3.14
Classifier: Programming Language :: Python :: Implementation :: CPython
Classifier: Programming Language :: Python :: Implementation :: PyPy
Classifier: Topic :: Internet :: WWW/HTTP
Classifier: Topic :: Multimedia :: Graphics
Classifier: Topic :: Utilities
Requires-Python: >=3.8
License-File: LICENSE
Requires-Dist: requests>=2.11.0
Provides-Extra: video
Requires-Dist: yt-dlp; extra == "video"
Provides-Extra: extra
Requires-Dist: requests[socks]; extra == "extra"
Requires-Dist: yt-dlp[default]; extra == "extra"
Requires-Dist: jinja2; extra == "extra"
Requires-Dist: pyyaml; extra == "extra"
Requires-Dist: toml; python_version < "3.11" and extra == "extra"
Requires-Dist: truststore; python_version >= "3.10" and extra == "extra"
Requires-Dist: secretstorage; sys_platform == "linux" and extra == "extra"
Dynamic: author
Dynamic: author-email
Dynamic: classifier
Dynamic: description
Dynamic: description-content-type
Dynamic: download-url
Dynamic: home-page
Dynamic: keywords
Dynamic: license
Dynamic: license-file
Dynamic: maintainer
Dynamic: maintainer-email
Dynamic: provides-extra
Dynamic: requires-dist
Dynamic: requires-python
Dynamic: summary
